easymode/__init__.py
easymode/main.py
easymode/core/__init__.py
easymode/core/augmentations.py
easymode/core/config.py
easymode/core/distribution.py
easymode/core/inference.py
easymode/core/model.py
easymode/core/packaging.py
easymode/core/settings.txt
easymode/core/train.py
easymode/core/warp.py
easymode/membrain_fourier_augmentations/__init__.py
easymode/membrain_fourier_augmentations/filter_utils.py
easymode/membrain_fourier_augmentations/fourier_augmentations.py
easymode/membrain_fourier_augmentations/transforms.py
easymode-0.0.1.dist-info/METADATA
easymode-0.0.1.dist-info/WHEEL
easymode-0.0.1.dist-info/entry_points.txt
easymode-0.0.1.dist-info/top_level.txt
easymode-0.0.1.dist-info/RECORD
